casting/apps/cast/cli/__init__.py
casting/apps/cast/cli/__main__.py
casting/apps/cast/cli/cli.py
casting/apps/cast/cli/gdoc.py
casting/apps/cast/cli/tui.py
casting/apps/cast/cli/tui_plugin.py
casting_cast_cli-0.2.5.dist-info/WHEEL
casting_cast_cli-0.2.5.dist-info/entry_points.txt
casting_cast_cli-0.2.5.dist-info/METADATA
casting_cast_cli-0.2.5.dist-info/RECORD
