Metadata-Version: 2.3
Name: casting-cast-cli
Version: 0.2.5
Summary: CLI for Cast Sync
Requires-Dist: casting-config
Requires-Dist: cast-core
Requires-Dist: cast-sync
Requires-Dist: cast-tui
Requires-Dist: typer>=0.9.0
Requires-Dist: rich>=13.0.0
Requires-Dist: ruamel-yaml>=0.18.0
Requires-Dist: prompt-toolkit>=3.0.43
Requires-Dist: google-api-python-client>=2.131.0
Requires-Dist: google-auth>=2.30.0
Requires-Dist: google-auth-oauthlib>=1.2.0
Requires-Python: >=3.13
